css_sprite/__init__.py
css_sprite/__main__.py
css_sprite/cli.py
css_sprite-0.2.0.dist-info/AUTHORS.rst
css_sprite-0.2.0.dist-info/LICENSE
css_sprite-0.2.0.dist-info/METADATA
css_sprite-0.2.0.dist-info/WHEEL
css_sprite-0.2.0.dist-info/entry_points.txt
css_sprite-0.2.0.dist-info/top_level.txt
css_sprite-0.2.0.dist-info/RECORD
